[{
  "bulan": "1",
  "total_penjualan": "6979330"
}, {
  "bulan": "2",
  "total_penjualan": "6515960"
}, {
  "bulan": "3",
  "total_penjualan": "7039710"
}, {
  "bulan": "4",
  "total_penjualan": "6873680"
}, {
  "bulan": "5",
  "total_penjualan": "7140275"
}, {
  "bulan": "6",
  "total_penjualan": "6823020"
}, {
  "bulan": "7",
  "total_penjualan": "7255790"
}, {
  "bulan": "8",
  "total_penjualan": "6827825"
}, {
  "bulan": "9",
  "total_penjualan": "6418005"
}, {
  "bulan": "10",
  "total_penjualan": "6402760"
}, {
  "bulan": "11",
  "total_penjualan": "7039535"
}, {
  "bulan": "12",
  "total_penjualan": "6470115"
}]